CHANGES.txt
MANIFEST.in
README.txt
setup.py
src/rsl/__init__.py
src/rsl/factories.py
src/rsl/globalregistry.py
src/rsl/implementations.py
src/rsl/interfaces.py
src/rsl/schema.py
src/rsl.egg-info/PKG-INFO
src/rsl.egg-info/SOURCES.txt
src/rsl.egg-info/dependency_links.txt
src/rsl.egg-info/entry_points.txt
src/rsl.egg-info/namespace_packages.txt
src/rsl.egg-info/requires.txt
src/rsl.egg-info/top_level.txt
src/rsl/misc/__init__.py
src/rsl/misc/boolean.py
src/rsl/misc/decorators.py
src/rsl/misc/http.py
src/rsl/misc/isodate.py
src/rsl/misc/namespace.py
src/rsl/misc/tzinfo.py
src/rsl/transport/__init__.py
src/rsl/transport/urllib2transport.py